Metadata-Version: 2.4
Name: geometry_toolkit_anas
Version: 0.1.0
Summary: A toolkit for basic geometric calculations
Home-page: https://github.com/syedanass/geometry_toolkit
Author: Anas Aijaz
Author-email: anas.aijaz.tech@gmail.com
Classifier: Programming Language :: Python :: 3
Classifier: License :: OSI Approved :: MIT License
Classifier: Operating System :: OS Independent
Requires-Python: >=3.6
License-File: LICENSE
Dynamic: author
Dynamic: author-email
Dynamic: classifier
Dynamic: description
Dynamic: description-content-type
Dynamic: home-page
Dynamic: license-file
Dynamic: requires-python
Dynamic: summary
